{
    "004822": "a person is walking in place.",
    "009613": "this",
    "008463": "a person walks forward at a normal pace.",
    "012498": "a person walks in place with arms swinging",
    "012883": "a person is walking in place.",
    "002139": "a person walks in place with arms swinging",
    "002606": "a person is walking in place.",
    "009968": "this",
    "012985": "a person walks forward at a normal pace.",
    "009977": "a person walks forward at a normal pace",
    "005477": "a person walks forward at a normal pace.",
    "004873": "a person walks forward at a normal pace",
    "011055": "a person is walking in place.",
    "012098": "a person walks forward at a normal pace.",
    "002662": "the person is walking normally on a treadmill",
    "001840": "a person is walking in place.",
    "009709": "a person is walking in place.",
    "008105": "a person walks forward at a normal pace.",
    "012032": "a person walks forward at a normal pace",
    "008998": "a person walks forward at a normal pace.",
    "011935": "the person is walking at a normal pace.",
    "002733": "a person walks in place with arms swinging",
    "002754": "a person is walking in place.",
    "010270": "the person is walking normally on a treadmill.",
    "010739": "a person walks forward, turns around and sits down, then stands up and walks back.",
    "010576": "a person is walking in place.",
    "008505": "a person walks in place with arms swinging",
    "004808": "the person is walking at a normal pace.",
    "010343": "the person is walking forward at a normal pace.",
    "011257": "a person walks in place with arms swinging",
    "004297": "a person is walking in place.",
    "008208": "specializing in a beautiful, easy to walk, and offering a welcome-to-loy at the end of your life. ed",
    "008888": "a person walks forward at a normal pace",
    "007551": "a person walks in place with arms swinging",
    "004120": "a person walks in place with arms swinging",
    "004504": "the person is walking at a normal pace.",
    "003255": "a person walks in place with arms swinging",
    "005037": "a person walks forward, turns around and sits down, then stands up and walks back.",
    "007676": "a person is walking in place.",
    "007089": "a person walks forward at a normal pace",
    "000091": "a person walks forward at a normal pace.",
    "013471": "a person is walking in place.",
    "014342": "a person walks in place with arms swinging",
    "000304": "a person walks in place with arms swinging",
    "013003": "this",
    "001648": "a person walks forward at a normal pace",
    "010618": "a person is walking in place.",
    "012686": "a person walks forward at a normal pace.",
    "002483": "a person walks in place with arms swinging",
    "013222": "a person walks forward at a normal pace.",
    "011035": "a person walks in place with arms swinging",
    "001250": "a person walks in place with arms swinging",
    "000178": "a person walks forward at a normal pace.",
    "003954": "a person walks in place with arms swinging",
    "010199": "a person walks forward at a normal pace",
    "014428": "a person is walking in place.",
    "005793": "the person is walking normally on a treadmill.",
    "006457": "the person is walking normally on a treadmill.",
    "006712": "a person walks in place with arms swinging",
    "013071": "a person walks in place with arms swinging",
    "013050": "the person is walking normally on a treadmill.",
    "004652": "a person walks forward at a normal pace.",
    "004719": "a person walks forward, turns around and sits down, then stands up and walks back.",
    "014536": "a person walks in place with arms swinging",
    "011629": "a person is walking in place.",
    "000339": "a person is walking in place.",
    "008500": "the person is walking normally on a treadmill.",
    "013336": "a person walks forward, turns around and sits down, then stands up and walks back.",
    "010126": "a person walks in place with arms swinging",
    "006674": "a person walks in place with arms swinging",
    "006005": "a person is walking in place.",
    "008822": "a person walks in place with arms swinging",
    "009349": "a person walks forward at a normal pace.",
    "008235": "the person is walking normally on a treadmill.",
    "006718": "a person walks in place with arms swinging",
    "013344": "a person walks in place with arms swinging",
    "008843": "a person is walking in place.",
    "008902": "a person walks in place with arms swinging",
    "000350": "a person walks in place with arms swinging",
    "013573": "a person walks in place slowly.",
    "009303": "the person is walking at a normal pace.",
    "008100": "a person walks in place with arms swinging",
    "005119": "a person walks in place with arms swinging",
    "004183": "a person walks in place with arms swinging",
    "001454": "a person walks forward at a normal pace.",
    "004864": "a person is walking in place.",
    "004811": "a person walks forward, turns around and sits down, then stands up and walks back.",
    "005504": "a person walks forward at a normal pace",
    "001463": "a person walks in place with arms swinging",
    "001533": "a person walks forward at a normal pace.",
    "013728": "a person walks in place with arms swinging",
    "003859": "a person walks forward at a normal pace",
    "005217": "a person walks forward at a normal pace, then turns around and sits down.",
    "006041": "a person walks in place with arms swinging",
    "000189": "a person walks in place with arms swinging",
    "011793": "a person walks in place with arms swinging",
    "008528": "the person is walking normally on a treadmill.",
    "011101": "a person walks in place with arms swinging",
    "M004822": "the person is walking normally on a treadmill.",
    "M009613": "the person is walking at a normal pace.",
    "M008463": "a person walks forward at a normal pace.",
    "M012498": "a person walks in place with arms swinging",
    "M012883": "a person is walking in place.",
    "M002139": "a person walks in place with arms swinging",
    "M002606": "a person walks in place with arms swinging",
    "M009968": "this is the perfect place to visit for a short, easy, and convenient trip. c/s",
    "M012985": "a person walks in place, bends over and picks something up.",
    "M009977": "a person walks in place with arms swinging",
    "M005477": "a person walks forward at a normal pace.",
    "M004873": "a person walks in place with arms swinging",
    "M011055": "the person is walking normally on a treadmill.",
    "M012098": "a person walks forward at a normal pace.",
    "M002662": "a person walks forward at a normal pace.",
    "M001840": "a person walks in place slowly.",
    "M009709": "a person is walking in place.",
    "M008105": "a person walks in place with arms swinging.",
    "M012032": "a person walks in place with arms swinging",
    "M008998": "a person walks forward at a normal pace.",
    "M011935": "a person walks forward at a normal pace.",
    "M002733": "a person walks in place with arms swinging",
    "M002754": "a person walks forward at a normal pace.",
    "M010270": "the person is walking normally on a treadmill.",
    "M010739": "the person is walking at a moderately fast pace.",
    "M010576": "a person is walking in place.",
    "M008505": "a person walks in place with arms swinging",
    "M004808": "a person walks forward at a normal pace.",
    "M010343": "the person is walking at a normal pace.",
    "M011257": "a person walks in place with arms swinging",
    "M004297": "a person is walking in place.",
    "M008208": "a person walks forward at a normal pace.",
    "M008888": "a person is walking in place.",
    "M007551": "the person is walking normally on a treadmill.",
    "M004120": "a person walks in place with arms swinging",
    "M004504": "a person walks forward at a normal pace.",
    "M003255": "a person walks in place with arms swinging",
    "M005037": "the person is walking forward at a normal pace.",
    "M007676": "a person is walking in place.",
    "M007089": "a person walks forward at a normal pace",
    "M000091": "a person walks in place with arms swinging",
    "M013471": "a person walks in place with arms swinging",
    "M014342": "a person walks forward at a normal pace.",
    "M000304": "a person walks in place with arms swinging",
    "M013003": "a person walks in a straight line at a moderately fast pace.",
    "M001648": "the person is walking normally on a treadmill.",
    "M010618": "a person is walking in place.",
    "M012686": "a person walks forward at a normal pace.",
    "M002483": "a person walks in place with arms swinging",
    "M013222": "a person walks forward at a normal pace.",
    "M011035": "a person walks in place with arms swinging",
    "M001250": "a person walks in place with arms swinging",
    "M000178": "a person walks forward at a normal pace.",
    "M003954": "a person is walking in place.",
    "M010199": "a person walks forward at a normal pace",
    "M014428": "a person walks in place with arms swinging",
    "M005793": "the person is walking normally on a treadmill.",
    "M006457": "the person is walking normally on a treadmill.",
    "M006712": "a person walks in place with arms swinging",
    "M013071": "a person is walking in place.",
    "M013050": "a person walks forward, turns around and sits down, then stands up and walks back.",
    "M004652": "a person walks forward at a normal pace.",
    "M004719": "the",
    "M014536": "a person walks in place with arms swinging",
    "M011629": "a person walks in place with arms swinging",
    "M000339": "a person walks forward at a normal pace.",
    "M008500": "the person is walking normally on a treadmill.",
    "M013336": "this",
    "M010126": "a person walks in place with arms swinging",
    "M006674": "a person walks in place with arms swinging",
    "M006005": "a person walks in place with arms swinging",
    "M008822": "a person walks in place with arms swinging",
    "M009349": "a person walks forward at a normal pace.",
    "M008235": "a person walks in place with arms swinging",
    "M006718": "a person walks forward at a normal pace",
    "M013344": "a person is walking in place.",
    "M008843": "a person walks in place with arms swinging",
    "M008902": "a person is walking in place.",
    "M000350": "a person walks in place with arms swinging",
    "M013573": "our office is located in the heart of San Francisco. Our office is open to the public and offers a wide range of services including car parking, food delivery, restaurant/camping facilities, as well as other community-oriented activities.",
    "M009303": "the person is walking in place. she is",
    "M008100": "a person walks forward at a normal pace, then turns around and sits down with arms stretched out in front of them.",
    "M005119": "a person walks in place with arms swinging",
    "M004183": "a person walks in place with arms swinging",
    "M001454": "a person walks forward at a normal pace.",
    "M004864": "a person walks forward at a normal pace.",
    "M004811": "this",
    "M005504": "a person is walking in place.",
    "M001463": "a person walks in place with arms swinging",
    "M001533": "the person is walking at a normal pace.",
    "M013728": "a person walks in place with arms swinging",
    "M003859": "a person walks forward at a normal pace",
    "M005217": "a person walks forward at a normal pace.",
    "M006041": "a person walks forward at a normal pace, starting with their right foot.",
    "M000189": "a person walks in place with arms swinging",
    "M011793": "a person walks in place with arms swinging",
    "M008528": "a person walks in place with arms swinging",
    "M011101": "the person is walking normally on a treadmill."
}